.bumpversion.cfg
.gitignore
LICENSE
MANIFEST.in
README.md
README.rst
makefile
pyargs-runner.py
register.py
setup.py
pyargs/__init__.py
pyargs/__main__.py
pyargs/arguments.py
pyargs/main.py
pyargs/runner.py
pyargs.egg-info/PKG-INFO
pyargs.egg-info/SOURCES.txt
pyargs.egg-info/dependency_links.txt
pyargs.egg-info/entry_points.txt
pyargs.egg-info/not-zip-safe
pyargs.egg-info/top_level.txt
tests/__init__.py
tests/curl_example.sh
tests/end_to_end_test.sh
tests/helpers.py
tests/hosts
tests/ping_example.sh
tests/ping_example_nl_m.sh
tests/reader_cmd.py
tests/sample_text
tests/test_args
tests/test_pyargs.py
tests/urls
tests/writer_cmd.py
tests/writer_to_reader_test.sh
tests/xargs_example.sh