Metadata-Version: 1.1
Name: pyargs
Version: 0.11.0
Summary: A python script to run commands in parallel (think xargs and GNU parallel) without intermixing the output.
Home-page: http://github.com/robertoblackwell/pyargs.git
Author: Robert Blackwell
Author-email: rob@whiteacorn.com
License: MIT
Keywords: xargs,parallel,cli
Platform: UNKNOWN
Classifier: Development Status :: 3 - Alpha
Classifier: License :: OSI Approved :: MIT License
Classifier: Programming Language :: Python :: 2.7
Classifier: Intended Audience :: System Administrators
Classifier: Topic :: System :: Systems Administration
Classifier: Topic :: Utilities
